examples/array_reversal.py
examples/bar_sort.py
examples/binary_search_tree.py
examples/breadth_first_search.py
examples/code_demo.py
examples/hello_world.py
examples/lazy_animation.py
examples/rectangle.py
examples/rectangle_no_context_manager.py
examples/updater_demo.py
examples/visuscript_presentation.py
old/bubble_sort.py
old/data_structures.py
old/insertion_sort.py
old/simple_animation.py
old/utility.py
old/deocclusion-presentation/deocclusion.py
old/presentation-with-animation/presentation-with-animation.py
visuscript/__init__.py
visuscript/_constructors.py
visuscript/_interpolable.py
visuscript/_invalidator.py
visuscript/_property_locker.py
visuscript/_utility.py
visuscript/animated_collection.py
visuscript/animation.py
visuscript/canvas.py
visuscript/code.py
visuscript/config.py
visuscript/connector.py
visuscript/constants.py
visuscript/drawable.py
visuscript/element.py
visuscript/lazy_object.py
visuscript/math_utility.py
visuscript/organizer.py
visuscript/primatives.py
visuscript/segment.py
visuscript/text.py
visuscript/updater.py
visuscript/cli/__init__.py
visuscript/cli/visuscript_cli.py
visuscript/cli/scripts/visuscript-animate
visuscript/cli/scripts/visuscript-slideshow
visuscript/fonts/Arimo/Arimo-Italic-VariableFont_wght.ttf
visuscript/fonts/Arimo/Arimo-VariableFont_wght.ttf
visuscript/fonts/Arimo/LICENSE.txt
visuscript/fonts/Arimo/README.txt
visuscript/fonts/LeagueMono-2.300/OFL.md
visuscript/fonts/LeagueMono-2.300/README.md
visuscript-0.1.0.dist-info/licenses/LICENCE
visuscript-0.1.0.dist-info/METADATA
visuscript-0.1.0.dist-info/WHEEL
visuscript-0.1.0.dist-info/entry_points.txt
visuscript-0.1.0.dist-info/top_level.txt
visuscript-0.1.0.dist-info/RECORD
