Metadata-Version: 2.4
Name: visuscript
Version: 0.1.0
Summary: A Vector-Graphics-Based Animation Library
Author-email: Joshua Zingale <joshua.thomas.zingale@gmail.com>
License-Expression: MIT
Project-URL: Homepage, https://github.com/joshua-zingale/visuscript
Classifier: Programming Language :: Python :: 3
Classifier: Operating System :: OS Independent
License-File: LICENCE
Requires-Dist: numpy
Requires-Dist: Pillow
Requires-Dist: svg.py
Requires-Dist: pygments
Dynamic: license-file
